pythondcs.py
pythondcspro.py
pythondcs-1.1.0.dist-info/licenses/LICENSE
pythondcs-1.1.0.dist-info/METADATA
pythondcs-1.1.0.dist-info/WHEEL
pythondcs-1.1.0.dist-info/top_level.txt
pythondcs-1.1.0.dist-info/zip-safe
pythondcs-1.1.0.dist-info/RECORD
